README.md
setup.cfg
setup.py
drf_app_generators/__init__.py
drf_app_generators/generators.py
drf_app_generators/helpers.py
drf_app_generators/utils.py
drf_app_generators.egg-info/PKG-INFO
drf_app_generators.egg-info/SOURCES.txt
drf_app_generators.egg-info/dependency_links.txt
drf_app_generators.egg-info/requires.txt
drf_app_generators.egg-info/top_level.txt
drf_app_generators/compliers/__init__.py
drf_app_generators/compliers/app.py
drf_app_generators/compliers/factory.py
drf_app_generators/compliers/field.py
drf_app_generators/compliers/model.py
drf_app_generators/management/__init__.py
drf_app_generators/management/commands/__init__.py
drf_app_generators/management/commands/app_update.py
drf_app_generators/management/commands/generate.py
drf_app_generators/templates/__init__.py
drf_app_generators/templates/admin.py
drf_app_generators/templates/apidoc.py
drf_app_generators/templates/apis.py
drf_app_generators/templates/apps.py
drf_app_generators/templates/factories.py
drf_app_generators/templates/filters.py
drf_app_generators/templates/init.py
drf_app_generators/templates/models.py
drf_app_generators/templates/permissions.py
drf_app_generators/templates/serializers.py
drf_app_generators/templates/tests.py